agentpress/agents/.env.example
agentpress/agents/simple_web_dev/agent.py
agentpress/agents/simple_web_dev/tools/files_tool.py
agentpress/agents/simple_web_dev/tools/terminal_tool.py
agentpress/cli.py
agentpress/db_connection.py
agentpress/llm.py
agentpress/processor/base_processors.py
agentpress/processor/llm_response_processor.py
agentpress/processor/standard/standard_results_adder.py
agentpress/processor/standard/standard_tool_executor.py
agentpress/processor/standard/standard_tool_parser.py
agentpress/processor/xml/xml_results_adder.py
agentpress/processor/xml/xml_tool_executor.py
agentpress/processor/xml/xml_tool_parser.py
agentpress/state_manager.py
agentpress/thread_manager.py
agentpress/thread_viewer_ui.py
agentpress/tool.py
agentpress/tool_registry.py
agentpress-0.1.12.dist-info/LICENSE
agentpress-0.1.12.dist-info/METADATA
agentpress-0.1.12.dist-info/WHEEL
agentpress-0.1.12.dist-info/entry_points.txt
agentpress-0.1.12.dist-info/RECORD
