Metadata-Version: 2.1
Name: agentpress
Version: 0.1.12
Summary: Building blocks for AI Agents
Home-page: https://github.com/kortix-ai/agentpress
License: MIT
Keywords: llm,ai,agents,ai agents,ai agent framework
Author: marko-kraemer
Author-email: mail@markokraemer.com
Requires-Python: >=3.9,<4.0
Classifier: Development Status :: 4 - Beta
Classifier: Intended Audience :: Developers
Classifier: License :: OSI Approved :: MIT License
Classifier: Programming Language :: Python :: 3
Classifier: Programming Language :: Python :: 3.9
Classifier: Programming Language :: Python :: 3.10
Classifier: Programming Language :: Python :: 3.11
Classifier: Programming Language :: Python :: 3.12
Classifier: Programming Language :: Python :: 3.13
Classifier: Topic :: Software Development :: Libraries :: Python Modules
Requires-Dist: agentops (>=0.3.10,<0.4.0)
Requires-Dist: aiosqlite (>=0.20.0,<0.21.0)
Requires-Dist: altair (==4.2.2)
Requires-Dist: asyncio (>=3.4.3,<4.0.0)
Requires-Dist: click (>=8.1.7,<9.0.0)
Requires-Dist: litellm (>=1.44.4,<2.0.0)
Requires-Dist: packaging (>=23.2,<24.0)
Requires-Dist: pytest (>=8.3.3,<9.0.0)
Requires-Dist: pytest-asyncio (>=0.24.0,<0.25.0)
Requires-Dist: python-dotenv (>=1.0.1,<2.0.0)
Requires-Dist: questionary (>=2.0.1,<3.0.0)
Requires-Dist: requests (>=2.31.0,<3.0.0)
Requires-Dist: setuptools (>=75.3.0,<76.0.0)
Requires-Dist: streamlit-quill (>=0.0.3,<0.0.4)
Project-URL: Repository, https://github.com/kortix-ai/agentpress
